{
    "idx": "982a1442-ed86-46c6-8425-a5b4869ee900",
    "text": "Какая линия получится от пересечения конуса плоскостью Р?",
    "atype": 0,
    "contains_img": true,
    "answers": [
        {
            "text": "Парабола",
            "is_correct": true
        },
        {
            "text": "Прямые",
            "is_correct": false
        },
        {
            "text": "Эллипс",
            "is_correct": false
        },
        {
            "text": "Окружность",
            "is_correct": false
        },
        {
            "text": "Гипербола",
            "is_correct": false
        }
    ]
}