{
    "idx": "f914104d-fcfa-43d7-92d0-2a7835c5b20c",
    "text": "Какой поверхности принадлежит точка К?",
    "atype": 0,
    "contains_img": true,
    "answers": [
        {
            "text": "Профильной плоскости",
            "is_correct": false
        },
        {
            "text": "Поверхности цилиндра",
            "is_correct": true
        },
        {
            "text": "Пверхности тора",
            "is_correct": false
        },
        {
            "text": "Горизонтальной плоскости",
            "is_correct": false
        },
        {
            "text": "Фронтальной плоскости",
            "is_correct": false
        }
    ]
}